Audiopy_ML/__init__.py
Audiopy_ML/autoaudio.py
Audiopy_ML-0.1.dist-info/LICENSE
Audiopy_ML-0.1.dist-info/METADATA
Audiopy_ML-0.1.dist-info/WHEEL
Audiopy_ML-0.1.dist-info/top_level.txt
Audiopy_ML-0.1.dist-info/RECORD
