Metadata-Version: 2.1
Name: Audiopy-ML
Version: 0.1
Summary: This is a python package useful for the automated audio preprocessing and feature extraction.
Author: Sairam Adithya
Author-email: sairamadithya2002@gmail.com
Classifier: Programming Language :: Python :: 3
Classifier: License :: OSI Approved :: MIT License
Classifier: Operating System :: OS Independent
Requires-Python: >=3.6
License-File: LICENSE
